FDTD/PEC2D_functions.py
FDTD/PEC3D_functions.py
FDTD/__init__.py
FDTD/commons.py
FDTD/display_fields2D.py
FDTD/display_fields3D.py
FDTD/fdtd2D.py
FDTD/fdtd3D.py
tests/__init__.py
tests/diffraction_on_slit_test_2D.py
tests/diffraction_on_slit_test_3D.py
AKFDTD-0.2.4.dist-info/LICENSE
AKFDTD-0.2.4.dist-info/METADATA
AKFDTD-0.2.4.dist-info/WHEEL
AKFDTD-0.2.4.dist-info/top_level.txt
AKFDTD-0.2.4.dist-info/RECORD
