Metadata-Version: 2.1
Name: AKFDTD
Version: 0.2.4
Summary: Finite difference time domain simulation (for slit diffraction)
Home-page: http://avkor.epizy.com
Author: Alexander V. Korovin
Author-email: a.v.korovin73@gmail.com
License: MIT
Classifier: Programming Language :: Python :: 3
Classifier: License :: OSI Approved :: MIT License
Classifier: Operating System :: OS Independent
Requires-Python: >=3.6
License-File: LICENSE
Requires-Dist: cupy
Requires-Dist: numpy
Requires-Dist: matplotlib
